.gitignore
.readthedocs.yml
LICENSE
MANIFEST.in
README.rst
pyproject.toml
setup.cfg
setup.py
cmastro/__init__.py
cmastro/cm.py
cmastro/plot.py
cmastro/version.py
cmastro.egg-info/PKG-INFO
cmastro.egg-info/SOURCES.txt
cmastro.egg-info/dependency_links.txt
cmastro.egg-info/not-zip-safe
cmastro.egg-info/requires.txt
cmastro.egg-info/top_level.txt
cmastro/cmaps/hesperia.csv
cmastro/cmaps/lacerta.csv
cmastro/cmaps/laguna.csv
docs/.DS_Store
docs/Makefile
docs/conf.py
docs/index.rst
docs/make.bat
docs/_static/.DS_Store
docs/_templates/.DS_Store
docs/_templates/autosummary/base.rst
docs/_templates/autosummary/class.rst
docs/_templates/autosummary/module.rst