Metadata-Version: 2.1
Name: cmastro
Version: 0.2
Summary: Colormaps for Astronomers
Home-page: https://github.com/adrn/cmastro
Author: Adrian M. Price-Whelan
Author-email: adrianmpw@gmail.com
License: MIT
Platform: UNKNOWN
Requires-Python: >=3.7
Provides-Extra: test
Provides-Extra: docs
